kinguin_client/__init__.py
kinguin_client/clients/__init__.py
kinguin_client/clients/balance_client.py
kinguin_client/clients/base_client.py
kinguin_client/clients/order_client.py
kinguin_client/clients/products_client.py
kinguin_client/kinguin.py
kinguin_client-0.2.0.dist-info/LICENSE.md
kinguin_client-0.2.0.dist-info/WHEEL
kinguin_client-0.2.0.dist-info/METADATA
kinguin_client-0.2.0.dist-info/RECORD
