Metadata-Version: 2.1
Name: kinguin-client
Version: 0.2.0
Summary: Python API wrapper for Kinguin
Home-page: https://github.com/rr00bbiinn/kinguin-client
Keywords: api,kinguin
Author: rr00bbiinn
Author-email: robin@itlandslaget.se
Requires-Python: >=3.6,<4.0
Classifier: Programming Language :: Python :: 3
Classifier: Programming Language :: Python :: 3.10
Classifier: Programming Language :: Python :: 3.6
Classifier: Programming Language :: Python :: 3.7
Classifier: Programming Language :: Python :: 3.8
Classifier: Programming Language :: Python :: 3.9
Project-URL: Repository, https://github.com/rr00bbiinn/kinguin-client
